{
    "token": "***",
    "job": "clone-repo",
    "ref": "refs/heads/main",
    "sha": "43a17dd171c72118a783936b1cba8c8fba6167ba",
    "repository": "fzinzun/github-actions",
    "repository_owner": "fzinzun",
    "repositoryUrl": "git://github.com/fzinzun/github-actions.git",
    "run_id": "980424513",
    "run_number": "12",
    "retention_days": "90",
    "actor": "fzinzun",
    "workflow": "GitHub Actions with Cache",
    "head_ref": "",
    "base_ref": "",
    "event_name": "push",
    "event": {
      "after": "43a17dd171c72118a783936b1cba8c8fba6167ba",
      "base_ref": null,
      "before": "c58ff411859bc4f804bfeb5f523c822c2c51ad9c",
      "commits": [
        {
          "author": {
            "email": "francisco_zinzun@discovery.com",
            "name": "fzinzun",
            "username": "fzinzun"
          },
          "committer": {
            "email": "francisco_zinzun@discovery.com",
            "name": "fzinzun",
            "username": "fzinzun"
          },
          "distinct": true,
          "id": "43a17dd171c72118a783936b1cba8c8fba6167ba",
          "message": "Testing cache",
          "timestamp": "2021-06-28T13:58:33-07:00",
          "tree_id": "40cc55ceda8648cc71b20facda942ed2a9827ac2",
          "url": "https://github.com/fzinzun/github-actions/commit/43a17dd171c72118a783936b1cba8c8fba6167ba"
        }
      ],
      "compare": "https://github.com/fzinzun/github-actions/compare/c58ff411859b...43a17dd171c7",
      "created": false,
      "deleted": false,
      "forced": true,
      "head_commit": {
        "author": {
          "email": "francisco_zinzun@discovery.com",
          "name": "fzinzun",
          "username": "fzinzun"
        },
        "committer": {
          "email": "francisco_zinzun@discovery.com",
          "name": "fzinzun",
          "username": "fzinzun"
        },
        "distinct": true,
        "id": "43a17dd171c72118a783936b1cba8c8fba6167ba",
        "message": "Testing cache",
        "timestamp": "2021-06-28T13:58:33-07:00",
        "tree_id": "40cc55ceda8648cc71b20facda942ed2a9827ac2",
        "url": "https://github.com/fzinzun/github-actions/commit/43a17dd171c72118a783936b1cba8c8fba6167ba"
      },
      "pusher": {
        "email": "zinzun@gmail.com",
        "name": "fzinzun"
      },
      "ref": "refs/heads/main",
      "repository": {
        "archive_url": "https://api.github.com/repos/fzinzun/github-actions/{archive_format}{/ref}",
        "archived": false,
        "assignees_url": "https://api.github.com/repos/fzinzun/github-actions/assignees{/user}",
        "blobs_url": "https://api.github.com/repos/fzinzun/github-actions/git/blobs{/sha}",
        "branches_url": "https://api.github.com/repos/fzinzun/github-actions/branches{/branch}",
        "clone_url": "https://github.com/fzinzun/github-actions.git",
        "collaborators_url": "https://api.github.com/repos/fzinzun/github-actions/collaborators{/collaborator}",
        "comments_url": "https://api.github.com/repos/fzinzun/github-actions/comments{/number}",
        "commits_url": "https://api.github.com/repos/fzinzun/github-actions/commits{/sha}",
        "compare_url": "https://api.github.com/repos/fzinzun/github-actions/compare/{base}...{head}",
        "contents_url": "https://api.github.com/repos/fzinzun/github-actions/contents/{+path}",
        "contributors_url": "https://api.github.com/repos/fzinzun/github-actions/contributors",
        "created_at": 1621537492,
        "default_branch": "main",
        "deployments_url": "https://api.github.com/repos/fzinzun/github-actions/deployments",
        "description": "Project to test github actions.",
        "disabled": false,
        "downloads_url": "https://api.github.com/repos/fzinzun/github-actions/downloads",
        "events_url": "https://api.github.com/repos/fzinzun/github-actions/events",
        "fork": false,
        "forks": 0,
        "forks_count": 0,
        "forks_url": "https://api.github.com/repos/fzinzun/github-actions/forks",
        "full_name": "fzinzun/github-actions",
        "git_commits_url": "https://api.github.com/repos/fzinzun/github-actions/git/commits{/sha}",
        "git_refs_url": "https://api.github.com/repos/fzinzun/github-actions/git/refs{/sha}",
        "git_tags_url": "https://api.github.com/repos/fzinzun/github-actions/git/tags{/sha}",
        "git_url": "git://github.com/fzinzun/github-actions.git",
        "has_downloads": true,
        "has_issues": true,
        "has_pages": false,
        "has_projects": true,
        "has_wiki": true,
        "homepage": null,
        "hooks_url": "https://api.github.com/repos/fzinzun/github-actions/hooks",
        "html_url": "https://github.com/fzinzun/github-actions",
        "id": 369311395,
        "issue_comment_url": "https://api.github.com/repos/fzinzun/github-actions/issues/comments{/number}",
        "issue_events_url": "https://api.github.com/repos/fzinzun/github-actions/issues/events{/number}",
        "issues_url": "https://api.github.com/repos/fzinzun/github-actions/issues{/number}",
        "keys_url": "https://api.github.com/repos/fzinzun/github-actions/keys{/key_id}",
        "labels_url": "https://api.github.com/repos/fzinzun/github-actions/labels{/name}",
        "language": "Starlark",
        "languages_url": "https://api.github.com/repos/fzinzun/github-actions/languages",
        "license": null,
        "master_branch": "main",
        "merges_url": "https://api.github.com/repos/fzinzun/github-actions/merges",
        "milestones_url": "https://api.github.com/repos/fzinzun/github-actions/milestones{/number}",
        "mirror_url": null,
        "name": "github-actions",
        "node_id": "MDEwOlJlcG9zaXRvcnkzNjkzMTEzOTU=",
        "notifications_url": "https://api.github.com/repos/fzinzun/github-actions/notifications{?since,all,participating}",
        "open_issues": 0,
        "open_issues_count": 0,
        "owner": {
          "avatar_url": "https://avatars.githubusercontent.com/u/3701383?v=4",
          "email": "zinzun@gmail.com",
          "events_url": "https://api.github.com/users/fzinzun/events{/privacy}",
          "followers_url": "https://api.github.com/users/fzinzun/followers",
          "following_url": "https://api.github.com/users/fzinzun/following{/other_user}",
          "gists_url": "https://api.github.com/users/fzinzun/gists{/gist_id}",
          "gravatar_id": "",
          "html_url": "https://github.com/fzinzun",
          "id": 3701383,
          "login": "fzinzun",
          "name": "fzinzun",
          "node_id": "MDQ6VXNlcjM3MDEzODM=",
          "organizations_url": "https://api.github.com/users/fzinzun/orgs",
          "received_events_url": "https://api.github.com/users/fzinzun/received_events",
          "repos_url": "https://api.github.com/users/fzinzun/repos",
          "site_admin": false,
          "starred_url": "https://api.github.com/users/fzinzun/starred{/owner}{/repo}",
          "subscriptions_url": "https://api.github.com/users/fzinzun/subscriptions",
          "type": "User",
          "url": "https://api.github.com/users/fzinzun"
        },
        "private": false,
        "pulls_url": "https://api.github.com/repos/fzinzun/github-actions/pulls{/number}",
        "pushed_at": 1624913923,
        "releases_url": "https://api.github.com/repos/fzinzun/github-actions/releases{/id}",
        "size": 15,
        "ssh_url": "git@github.com:fzinzun/github-actions.git",
        "stargazers": 0,
        "stargazers_count": 0,
        "stargazers_url": "https://api.github.com/repos/fzinzun/github-actions/stargazers",
        "statuses_url": "https://api.github.com/repos/fzinzun/github-actions/statuses/{sha}",
        "subscribers_url": "https://api.github.com/repos/fzinzun/github-actions/subscribers",
        "subscription_url": "https://api.github.com/repos/fzinzun/github-actions/subscription",
        "svn_url": "https://github.com/fzinzun/github-actions",
        "tags_url": "https://api.github.com/repos/fzinzun/github-actions/tags",
        "teams_url": "https://api.github.com/repos/fzinzun/github-actions/teams",
        "trees_url": "https://api.github.com/repos/fzinzun/github-actions/git/trees{/sha}",
        "updated_at": "2021-06-28T20:55:40Z",
        "url": "https://github.com/fzinzun/github-actions",
        "watchers": 0,
        "watchers_count": 0
      },
      "sender": {
        "avatar_url": "https://avatars.githubusercontent.com/u/3701383?v=4",
        "events_url": "https://api.github.com/users/fzinzun/events{/privacy}",
        "followers_url": "https://api.github.com/users/fzinzun/followers",
        "following_url": "https://api.github.com/users/fzinzun/following{/other_user}",
        "gists_url": "https://api.github.com/users/fzinzun/gists{/gist_id}",
        "gravatar_id": "",
        "html_url": "https://github.com/fzinzun",
        "id": 3701383,
        "login": "fzinzun",
        "node_id": "MDQ6VXNlcjM3MDEzODM=",
        "organizations_url": "https://api.github.com/users/fzinzun/orgs",
        "received_events_url": "https://api.github.com/users/fzinzun/received_events",
        "repos_url": "https://api.github.com/users/fzinzun/repos",
        "site_admin": false,
        "starred_url": "https://api.github.com/users/fzinzun/starred{/owner}{/repo}",
        "subscriptions_url": "https://api.github.com/users/fzinzun/subscriptions",
        "type": "User",
        "url": "https://api.github.com/users/fzinzun"
      }
    },
    "server_url": "https://github.com",
    "api_url": "https://api.github.com",
    "graphql_url": "https://api.github.com/graphql",
    "workspace": "/home/runner/work/github-actions/github-actions",
    "action": "run",
    "event_path": "/home/runner/work/_temp/_github_workflow/event.json",
    "action_repository": "",
    "action_ref": "",
    "path": "/home/runner/work/_temp/_runner_file_commands/add_path_0a12dde5-0824-4c6e-95ec-c659bd485201",
    "env": "/home/runner/work/_temp/_runner_file_commands/set_env_0a12dde5-0824-4c6e-95ec-c659bd485201"
  }
